pykeutilsfastapi/__init__.py
pykeutilsfastapi/keycloak/__init__.py
pykeutilsfastapi/keycloak/_keycloak_auth.py
pykeutilsfastapi/redis/__init__.py
pykeutilsfastapi/redis/_auth_deco.py
pykeutilsfastapi/sqlalchemy/__init__.py
pykeutilsfastapi/sqlalchemy/_session_handler.py
pykeutilsfastapi/tenant/__init__.py
pykeutilsfastapi/tenant/_tenant.py
pykeutilsfastapi/tenant/_utils.py
py_ke_utils_fastapi-2.2.7.dist-info/METADATA
py_ke_utils_fastapi-2.2.7.dist-info/WHEEL
py_ke_utils_fastapi-2.2.7.dist-info/top_level.txt
py_ke_utils_fastapi-2.2.7.dist-info/RECORD
