Metadata-Version: 2.1
Name: py-ke-utils-fastapi
Version: 2.2.7
Summary: Utilities for FastAPI
Author: KE
Author-email: 
Keywords: python,FastAPI,PyJWT,decorator,token
Classifier: Development Status :: 1 - Planning
Classifier: Intended Audience :: Developers
Classifier: Programming Language :: Python :: 3.11
Classifier: Programming Language :: Python :: 3.12
Classifier: Operating System :: Unix
Classifier: Operating System :: MacOS
Requires-Dist: redis (>=4.5.0)
Requires-Dist: deepdiff (>=6.2.1)
Requires-Dist: fastapi (>=0.90)
Requires-Dist: SQLAlchemy (>=2.0.1)
Requires-Dist: alembic (>=1.10)
Requires-Dist: py-frameless-utils (>=0.1.3)
